{
    "men_comment_id": "10565374",
    "men_link_id": "1596658",
    "men_user_id": "ThePetersellers",
    "men_link": "https:\/\/www.meneame.net\/story\/cat-irregularidad-permite-mossos-seleccionen-juez-dictamina\/c02#c-2",
    "men_description": "Me parece que tenemos una jueza candidata a ser expulsada de la carrera judicial, y sera por las buenas, o por las malas. <mark>Tiempo al tiempo<\/mark>. \nrelacionada: www.meneame.net\/story\/senoria",
    "men_pubdate": "abril 2012",
    "men_votes": "52",
    "men_order": "2",
    "men_karma": "465",
    "men_title": "Una irregularidad permite que los Mossos seleccionen el juez que dictamina prisi\u00f3n preventiva [CAT]"
}