{
    "men_comment_id": "10619404",
    "men_link_id": "1604473",
    "men_user_id": "amimeconvirtioengrillo",
    "men_link": "https:\/\/www.meneame.net\/story\/nuevo-presidente-sgae-banda-ancha-innecesaria-emplea-descargar\/c07#c-7",
    "men_description": "Haciendo amigos desde el primer d\u00eda, si se\u00f1or. Le <mark>auguro<\/mark> unas cuantas portadas en esta web.",
    "men_pubdate": "mayo 2012",
    "men_votes": "34",
    "men_order": "7",
    "men_karma": "264",
    "men_title": "Nuevo presidente de la SGAE: la banda ancha es innecesaria y se emplea para \"descargar megas y megas\"   \u00a0"
}