{
    "men_comment_id": "15662358",
    "men_link_id": "2283346",
    "men_user_id": "sebiyorum",
    "men_link": "https:\/\/www.meneame.net\/story\/sanchez-rompe-rubalcaba-negocia-pactos-anticorrupcion-pp-acosado\/c013#c-13",
    "men_description": "#6 o peor tu te callas de lo mio y yo hago lo mismo con lo tuyo y aqu\u00ed no se entera ni el tato.\nSe acab\u00f3 las amenazas de que pueden aliarse, hacer un pacto contra la amenaza de Podemos, etc el autentico y real PPSOE ya se ha rubricado. Le <mark>auguro<\/mark> un corto camino a la desaparici\u00f3n del PSOE, por si alg\u00fan votante del SOE tenia dudas.",
    "men_pubdate": "octubre 2014",
    "men_votes": "14",
    "men_order": "13",
    "men_karma": "115",
    "men_title": "S\u00e1nchez rompe con Rubalcaba y negocia pactos anticorrupci\u00f3n con un PP acosado por los esc\u00e1ndalos"
}