{
    "men_comment_id": "17945831",
    "men_link_id": "2495575",
    "men_user_id": "Serujio85",
    "men_link": "https:\/\/www.meneame.net\/story\/airconsole-consola-virtual-puedes-controlar-tu-smartphone\/c016#c-16",
    "men_description": "No me puedo imaginar un mando peor que un tel\u00e9fono m\u00f3vil. Se supone que cuando uno mira la pantalla no tiene tiempo para mirar al mando para ver si est\u00e1 pulsando el bot\u00f3n correcto. Es necesario que el control tenga algo de relieve y usar el tacto para pulsar el bot\u00f3n correcto.\nLe <mark>auguro<\/mark> poco exito.",
    "men_pubdate": "octubre 2015",
    "men_votes": "12",
    "men_order": "16",
    "men_karma": "72",
    "men_title": "AirConsole, la consola virtual que puedes controlar con tu smartphone"
}