{
    "men_comment_id": "19836962",
    "men_link_id": "2638818",
    "men_user_id": "--471299--",
    "men_link": "https:\/\/www.meneame.net\/story\/trama-ave-uso-material-menor-calidad-desviar-hasta-82-millones\/c017#c-17",
    "men_description": "Eso, si ocurre un accidente, es homicidio involuntario por cada pasajero. \nEn Estados Unidos irian a la carcel. \nEn China ser\u00edan ejecutados. \nEn Francia ya estar\u00edan en la carcel. \nEn Espa\u00f1a no van a pisar una celda. <mark>Tiempo al tiempo<\/mark>.",
    "men_pubdate": "junio 2016",
    "men_votes": "35",
    "men_order": "17",
    "men_karma": "235",
    "men_title": "La trama del AVE us\u00f3 material de menor calidad para desviar hasta 82 millones de euros"
}