{
    "men_comment_id": "24088282",
    "men_link_id": "2930621",
    "men_user_id": "MatiasElTostao",
    "men_link": "https:\/\/www.meneame.net\/story\/ciudadanos-rompe-negociacion-pp-solo-acepta-dimision-cifuentes\/c015#c-15",
    "men_description": "No tardando mucho escucharemos decir a Rivera que Cifuentes ha dimitido gracias a la presi\u00f3n de ciudadanos. Y sino <mark>tiempo al tiempo<\/mark>...\n\nMe guardo el comentario a modo de prueba ",
    "men_pubdate": "abril 2018",
    "men_votes": "20",
    "men_order": "15",
    "men_karma": "148",
    "men_title": "Ciudadanos rompe la negociaci\u00f3n con el PP y s\u00f3lo acepta la dimisi\u00f3n de Cifuentes"
}