{
    "men_comment_id": "29433840",
    "men_link_id": "3287761",
    "men_user_id": "\ufede\u03b1\u028b\u03b9\u04bd\u027e\u03b1\u1e9e",
    "men_link": "https:\/\/www.meneame.net\/story\/peon-vineta-manel-fontdevila\/c01#c-1",
    "men_description": "Vi\u00f1eta dejando mal a S\u00e1nchez, poco futuro le <mark>auguro<\/mark>.",
    "men_pubdate": "abril 2020",
    "men_votes": "20",
    "men_order": "1",
    "men_karma": "207",
    "men_title": "  El pe\u00f3n. Vi\u00f1eta de Manel Fontdevila   \u00a0  "
}