{
    "men_comment_id": "3746151",
    "men_link_id": "615875",
    "men_user_id": "--83516--",
    "men_link": "https:\/\/www.meneame.net\/story\/presidente-tsjv-intimo-amigo-camps-investigaria-presunta-gurtel\/c013#c-13",
    "men_description": "Veo alguna cara de extra\u00f1eza por aqu\u00ed, para los que no sois de valencia, deber\u00edais saber que valencia es como la finca feudal de el PPCV, aqu\u00ed campan a sus anchas, haciendo lo que quieren y deshaciendo lo que les apetece, y encima la gente encantada con su venda en los ojos, disfrutando de la Ciutat de les Arts i les Ciencies, el Circuito de F1, Terra M\u00edtica (de esto no tanto), el Nuevo Mestalla, las Fallas, sin darse cuenta que est\u00e1n endeudando toda la comunidad, que dentro de poco no habr\u00e1 dinero para pagar ni siquiera los funcionarios, las universidades ya no cobran, ...\n\nPero, desde aqu\u00ed, <mark>vaticino<\/mark> una cosa, si el VCF entra en suspensi\u00f3n de pagos, valencia entera saldr\u00e1 a la calle clamando como si el mundo fuese a acabarse, y Camps endeudar\u00e1 mas la comunidad para sacarlo de la mierda.\n\nHay veces que me da asco vivir en valencia.\n\nPD: Por si no lo hab\u00edais entendido, Camps se ir\u00e1 de rositas, no pisar\u00e1 una celda en su vida, de hecho, dudo que dimita, como mucho se ir\u00e1 de putas con Fabra con el dinero de todos nosotros.",
    "men_pubdate": "marzo 2009",
    "men_votes": "19",
    "men_order": "13",
    "men_karma": "164",
    "men_title": "El presidente del TSJV, \u00edntimo amigo de Camps, investigar\u00eda su presunta implicaci\u00f3n en la Operaci\u00f3n G\u00fcrtel"
}